{
    "done": false,
    "elements": {
        "Cognizer - nsubj": "A0-PAG",
        "Phenomenon - ccomp": "A1-PPT",
        "Phenomenon - obj": null,
        "Time - advmod": "AM-TMP",
        "Topic - iobj": null
    },
    "predicate": "find_out.03",
    "samples": {
        "zinﾄ》.a-d121-p423s2.8": {
            "state": "ok"
        },
        "zinﾄ》.a-d85-p142s5.4": {
            "state": "ok"
        },
        "zinﾄ》.a-p17127-p4s3.23": {
            "state": "ok"
        },
        "zinﾄ》.a-p17127-p4s4.16": {
            "state": "ok"
        }
    }
}