{
    "done": true,
    "elements": {
        "Expressor - nsubj": "A1-PPT",
        "Speaker - nsubj": "A1-PPT",
        "Time - obl": "AM-TMP"
    },
    "predicate": "quiet.03",
    "samples": {
        "apklust.a-d144-p153s1.2": {
            "state": "ok"
        },
        "apklust.a-d16-p93s11.5": {
            "state": "ok"
        },
        "apklust.a-d197-p39s1.2": {
            "state": "ok"
        },
        "apklust.a-d2-p420s2.3": {
            "state": "ok"
        },
        "apklust.a-d30-p356s1.2": {
            "state": "ok"
        },
        "apklust.a-p4-p31s5.5": {
            "state": "ok"
        },
        "apklust.a-p9-p4s1.11": {
            "state": "ok"
        }
    }
}