{
    "done": true,
    "elements": {
        "Agent - nsubj": "A0-PAG",
        "Medium - obl": "AM-LOC",
        "Perceiver - iobj": "A2-GOL",
        "Phenomenon - nsubj:pass": "A1-PPT",
        "Phenomenon - obj": "A1-PPT",
        "Place - obl": "AM-LOC",
        "Time - obl": "AM-TMP"
    },
    "predicate": "demonstrate.01",
    "samples": {
        "prezentēt.a-p12991-p1s1.26": {
            "state": "ok"
        },
        "prezentēt.a-p15009-p5s1.6": {
            "state": "ok"
        },
        "prezentēt.a-p3753-p10s1.19": {
            "state": "ok"
        },
        "prezentēt.a-p3758-p1s1.0": {
            "state": "ok"
        },
        "prezentēt.a-p3768-p4s1.7": {
            "state": "ok"
        },
        "prezentēt.a-p3773-p2s2.32": {
            "state": "ok"
        },
        "prezentēt.a-z107-p162s1.14": {
            "state": "ok"
        },
        "prezentēt.a-z107-p162s5.5": {
            "state": "ok"
        }
    }
}