{
    "done": true,
    "elements": {
        "Agent - nsubj": "A0-PAG",
        "Container_portal - obj": "A1-PPT",
        "Containing_object - obj": "A1-PPT"
    },
    "predicate": "close.01",
    "samples": {
        "aizvērt.a-d199-p12s1.3": {
            "state": "ok"
        },
        "aizvērt.a-d199-p16s2.20": {
            "state": "ok"
        },
        "aizvērt.a-d199-p42s1.7": {
            "state": "ok"
        },
        "aizvērt.a-d200-p26s1.0": {
            "state": "ok"
        },
        "aizvērt.a-p3766-p6s6.11": {
            "state": "ok"
        }
    }
}