{
    "done": false,
    "elements": {
        "Partner_1 - nsubj": "A0-PAG",
        "Partner_2 - iobj": "A1-COM",
        "Partners - iobj": null,
        "Partners - nsubj": "A0-PAG",
        "Time - advmod": null,
        "Time - obl": null,
        "Undertaking - advcl": null,
        "Undertaking - obl": null
    },
    "predicate": "collaborate.01",
    "samples": {
        "sadarboties.a-c57-p4s10.5": {
            "state": "ok"
        },
        "sadarboties.a-p11461-p3s2.1": {
            "state": "ok"
        },
        "sadarboties.a-p11470-p4s3.1": {
            "state": "ok"
        },
        "sadarboties.a-p12073-p6s1.2": {
            "state": "ok"
        },
        "sadarboties.a-p12163-p8s2.11": {
            "state": "ok"
        },
        "sadarboties.a-p13126-p5s1.3": {
            "state": "ok"
        },
        "sadarboties.a-p15687-p4s1.12": {
            "state": "ok"
        },
        "sadarboties.a-p1604-p2s2.8": {
            "state": "ok"
        },
        "sadarboties.a-p19300-p5s1.17": {
            "state": "ok"
        },
        "sadarboties.a-p2644-p6s1.6": {
            "state": "ok"
        },
        "sadarboties.a-p2812-p4s2.1": {
            "state": "ok"
        },
        "sadarboties.a-p3745-p1s1.6": {
            "state": "ok"
        },
        "sadarboties.a-p3751-p2s5.6": {
            "state": "ok"
        },
        "sadarboties.a-p3754-p31s1.7": {
            "state": "ok"
        },
        "sadarboties.a-p3762-p51s1.3": {
            "state": "ok"
        },
        "sadarboties.a-p3762-p52s1.15": {
            "state": "ok"
        },
        "sadarboties.a-p477-p16s4.23": {
            "state": "ok"
        },
        "sadarboties.a-s39-p6s4.18": {
            "state": "ok"
        }
    }
}