{
    "done": false,
    "elements": {
        "Message - ccomp": null,
        "Message - nsubj:pass": null,
        "Message - obj": null,
        "Message - parataxis": null,
        "Speaker - nsubj": null
    },
    "predicate": null,
    "samples": {
        "akcentēt.a-p16069-p4s4.16": {
            "state": "ok"
        },
        "akcentēt.a-p18723-p4s2.1": {
            "state": "ok"
        },
        "akcentēt.a-p3098-p47s3.32": {
            "state": "ok"
        },
        "akcentēt.a-z107-p40s3.12": {
            "state": "ok"
        },
        "akcentēt.a-z51-p17s1.6": {
            "state": "ok"
        },
        "akcentēt.a-z89-p281s1.16": {
            "state": "ok"
        }
    }
}