{
    "done": false,
    "elements": {
        "Cotheme - iobj": null,
        "Cotheme - obj": null,
        "Direction - advmod": null,
        "Direction - obl": null,
        "Goal - iobj": null,
        "Goal - obl": null,
        "Path - obl": null,
        "Source - obl": null,
        "Theme - nsubj": null,
        "Theme - obj": null,
        "Time - advmod": null
    },
    "predicate": null,
    "samples": [
        "vest.a-c15-p36s3",
        "vest.a-d1-p729s2",
        "vest.a-d119-p299s3",
        "vest.a-d135-p162s1",
        "vest.a-d137-p1519s1",
        "vest.a-d140a-p653s5",
        "vest.a-d62-p14s9",
        "vest.a-p3325-p32s1",
        "vest.a-p378-p11s1",
        "vest.a-p390-p20s1",
        "vest.a-p633-p9s3",
        "vest.a-p656-p33s2",
        "vest.a-p656-p33s4"
    ]
}