{
    "done": true,
    "elements": {
        "Cause - nsubj": "A0-PAG",
        "Cause - nsubj:pass": "A0-PAG",
        "Cause - obl": "A0-PAG",
        "Created_entity - nsubj": "A1-PPT",
        "Created_entity - obj": "A1-PPT",
        "Creator - nsubj": "A0-PAG",
        "Place - obl": "AM-LOC"
    },
    "predicate": "leave.13",
    "samples": {
        "atstāt.a-c29-p3s13.2": {
            "state": "ok"
        },
        "atstāt.a-d27-p16s5.42": {
            "state": "ok"
        },
        "atstāt.a-d30-p356s2.15": {
            "state": "ok"
        },
        "atstāt.a-p2420-p2s1.0": {
            "state": "ok"
        },
        "atstāt.a-p2774-p17s1.12": {
            "state": "ok"
        },
        "atstāt.a-p3754-p13s2.18": {
            "state": "ok"
        },
        "atstāt.a-p3754-p14s3.9": {
            "state": "ok"
        },
        "atstāt.a-p586-p18s2.11": {
            "state": "ok"
        },
        "atstāt.a-p8293-p10s2.20": {
            "state": "ok"
        },
        "atstāt.a-p899-p23s3.12": {
            "state": "ok"
        },
        "atstāt.a-p9117-p15s1.28": {
            "state": "ok"
        },
        "atstāt.a-z46-p13s1.12": {
            "state": "ok"
        },
        "atstāt.a-z46-p13s5.24": {
            "state": "ok"
        }
    }
}