{
    "done": true,
    "elements": {
        "Ingestibles - obj": "A1-PPT",
        "Ingestor - compound": "A0-PAG",
        "Ingestor - nsubj": "A0-PAG",
        "Place - advmod": "AM-LOC",
        "Place - obl": "AM-LOC",
        "Time - advmod": "AM-TMP",
        "Time - conj": "AM-TMP",
        "Time - obl": "AM-TMP"
    },
    "predicate": "eat.01",
    "samples": {
        "ēst.a-d180-p1578s2.2": {
            "state": "ok"
        },
        "ēst.a-d200-p87s1.16": {
            "state": "ok"
        },
        "ēst.a-d27-p14s3.20": {
            "state": "ok"
        },
        "ēst.a-d29-p82s18.3": {
            "state": "ok"
        },
        "ēst.a-d62-p33s7.4": {
            "state": "ok"
        },
        "ēst.a-d7-p25s1.4": {
            "state": "ok"
        },
        "ēst.a-d78-p17s5.33": {
            "state": "ok"
        },
        "ēst.a-d78-p17s6.7": {
            "state": "ok"
        },
        "ēst.a-d83-p155s9.6": {
            "state": "ok"
        },
        "ēst.a-p10467-p2s1.15": {
            "state": "ok"
        },
        "ēst.a-p11612-p9s1.9": {
            "state": "ok"
        },
        "ēst.a-p11612-p9s2.11": {
            "state": "ok"
        },
        "ēst.a-p1176-p3s5.5": {
            "state": "ok"
        },
        "ēst.a-p12555-p1s2.32": {
            "state": "ok"
        },
        "ēst.a-p13947-p37s3.18": {
            "state": "ok"
        },
        "ēst.a-p18709-p3s2.8": {
            "state": "ok"
        },
        "ēst.a-p19593-p3s6.13": {
            "state": "ok"
        },
        "ēst.a-p2812-p4s1.16": {
            "state": "ok"
        },
        "ēst.a-p2994-p10s4.3": {
            "state": "ok"
        },
        "ēst.a-p3151-p11s1.10": {
            "state": "ok"
        },
        "ēst.a-p3298-p19s1.3": {
            "state": "ok"
        },
        "ēst.a-p3533-p2s4.15": {
            "state": "ok"
        },
        "ēst.a-p4963-p60s1.13": {
            "state": "ok"
        },
        "ēst.a-p5446-p3s1.16": {
            "state": "ok"
        },
        "ēst.a-p5446-p3s2.9": {
            "state": "ok"
        },
        "ēst.a-p5446-p3s7.11": {
            "state": "ok"
        },
        "ēst.a-p5613-p4s1.17": {
            "state": "ok"
        },
        "ēst.a-p5777-p12s1.14": {
            "state": "ok"
        },
        "ēst.a-p595-p8s2.12": {
            "state": "ok"
        },
        "ēst.a-p6786-p13s1.8": {
            "state": "ok"
        },
        "ēst.a-p7489-p4s1.16": {
            "state": "ok"
        },
        "ēst.a-p7605-p5s3.14": {
            "state": "ok"
        },
        "ēst.a-s14-p122s1.17": {
            "state": "ok"
        }
    }
}