{
    "done": true,
    "elements": {
        "Act - advmod": "A1-PPT",
        "Act - ccomp": "A1-PPT",
        "Act - discourse": "A1-PPT",
        "Act - iobj": "A1-PPT",
        "Act - nsubj": "A1-PPT",
        "Act - nsubj:pass": "A1-PPT",
        "Act - obj": "A1-PPT",
        "Agent - iobj": "A0-PAG",
        "Agent - nsubj": "A0-PAG",
        "Agent - obj": "A0-PAG",
        "Place - advmod": "AM-LOC",
        "Place - obl": "AM-LOC",
        "Time - advmod": "AM-TMP",
        "Time - obl": "AM-TMP"
    },
    "predicate": "do.02",
    "samples": {
        "darīt.a-c32-p7s5.3": {
            "state": "ok"
        },
        "darīt.a-c60-p10s2.8": {
            "state": "ok"
        },
        "darīt.a-c60-p28s1.17": {
            "state": "ok"
        },
        "darīt.a-c60-p29s1.8": {
            "state": "ok"
        },
        "darīt.a-c60-p3s5.16": {
            "state": "ok"
        },
        "darīt.a-d117-p385s5.2": {
            "state": "ok"
        },
        "darīt.a-d119-p292s1.6": {
            "state": "ok"
        },
        "darīt.a-d124-p175s4.1": {
            "state": "ok"
        },
        "darīt.a-d140-p32s17.1": {
            "state": "ok"
        },
        "darīt.a-d140a-p286s3.0": {
            "state": "ok"
        },
        "darīt.a-d197-p138s3.3": {
            "state": "ok"
        },
        "darīt.a-d199-p26s2.3": {
            "state": "ok"
        },
        "darīt.a-d199-p26s2.7": {
            "state": "ok"
        },
        "darīt.a-d199-p33s5.4": {
            "state": "ok"
        },
        "darīt.a-d200-p54s2.11": {
            "state": "ok"
        },
        "darīt.a-d200-p62s1.6": {
            "state": "ok"
        },
        "darīt.a-d200-p89s2.2": {
            "state": "ok"
        },
        "darīt.a-d28-p225s2.17": {
            "state": "ok"
        },
        "darīt.a-d8-p58s5.3": {
            "state": "ok"
        },
        "darīt.a-p10100-p8s1.6": {
            "state": "ok"
        },
        "darīt.a-p10611-p1s5.25": {
            "state": "ok"
        },
        "darīt.a-p10978-p2s1.45": {
            "state": "ok"
        },
        "darīt.a-p11022-p5s2.5": {
            "state": "ok"
        },
        "darīt.a-p11461-p3s4.9": {
            "state": "ok"
        },
        "darīt.a-p11517-p1s3.2": {
            "state": "ok"
        },
        "darīt.a-p11560-p6s2.5": {
            "state": "ok"
        },
        "darīt.a-p11620-p9s2.6": {
            "state": "ok"
        },
        "darīt.a-p12530-p1s9.6": {
            "state": "ok"
        },
        "darīt.a-p12652-p1s4.7": {
            "state": "ok"
        },
        "darīt.a-p12783-p5s4.21": {
            "state": "ok"
        },
        "darīt.a-p12815-p7s4.9": {
            "state": "ok"
        },
        "darīt.a-p13256-p5s2.3": {
            "state": "ok"
        },
        "darīt.a-p13270-p6s1.39": {
            "state": "ok"
        },
        "darīt.a-p1494-p5s10.6": {
            "state": "ok"
        },
        "darīt.a-p1494-p5s11.6": {
            "state": "ok"
        },
        "darīt.a-p15673-p3s3.2": {
            "state": "ok"
        },
        "darīt.a-p15673-p3s4.7": {
            "state": "ok"
        },
        "darīt.a-p1597-p10s1.1": {
            "state": "ok"
        },
        "darīt.a-p1626-p7s2.24": {
            "state": "ok"
        },
        "darīt.a-p16809-p2s1.27": {
            "state": "ok"
        },
        "darīt.a-p16833-p3s1.22": {
            "state": "ok"
        },
        "darīt.a-p17992-p7s1.13": {
            "state": "wrong_elemnt"
        },
        "darīt.a-p17992-p7s1.24": {
            "state": "ok"
        },
        "darīt.a-p18200-p5s4.3": {
            "state": "ok"
        },
        "darīt.a-p18200-p5s4.6": {
            "state": "ok"
        },
        "darīt.a-p2098-p7s2.8": {
            "state": "ok"
        },
        "darīt.a-p291-p9s1.20": {
            "state": "ok"
        },
        "darīt.a-p3135-p11s4.15": {
            "state": "ok"
        },
        "darīt.a-p3189-p3s2.13": {
            "state": "ok"
        },
        "darīt.a-p3207-p4s2.10": {
            "state": "ok"
        },
        "darīt.a-p3300-p32s3.12": {
            "state": "ok"
        },
        "darīt.a-p3300-p32s6.3": {
            "state": "ok"
        },
        "darīt.a-p3311-p19s3.1": {
            "state": "ok"
        },
        "darīt.a-p3311-p25s9.7": {
            "state": "ok"
        },
        "darīt.a-p3311-p38s2.0": {
            "state": "ok"
        },
        "darīt.a-p3312-p14s4.10": {
            "state": "ok"
        },
        "darīt.a-p3340-p11s1.11": {
            "state": "ok"
        },
        "darīt.a-p3351-p6s3.6": {
            "state": "ok"
        },
        "darīt.a-p340-p14s4.1": {
            "state": "ok"
        },
        "darīt.a-p3753-p32s1.10": {
            "state": "ok"
        },
        "darīt.a-p3754-p15s5.9": {
            "state": "ok"
        },
        "darīt.a-p3754-p15s8.10": {
            "state": "ok"
        },
        "darīt.a-p3754-p8s4.1": {
            "state": "ok"
        },
        "darīt.a-p3757-p3s3.14": {
            "state": "ok"
        },
        "darīt.a-p3757-p3s3.17": {
            "state": "ok"
        },
        "darīt.a-p3761-p2s1.1": {
            "state": "ok"
        },
        "darīt.a-p3762-p46s3.1": {
            "state": "ok"
        },
        "darīt.a-p3762-p48s6.5": {
            "state": "ok"
        },
        "darīt.a-p3762-p52s3.7": {
            "state": "ok"
        },
        "darīt.a-p3762-p58s7.23": {
            "state": "ok"
        },
        "darīt.a-p3762-p8s1.14": {
            "state": "ok"
        },
        "darīt.a-p387-p17s5.13": {
            "state": "ok"
        },
        "darīt.a-p503-p7s7.7": {
            "state": "ok"
        },
        "darīt.a-p510-p11s1.12": {
            "state": "ok"
        },
        "darīt.a-p5292-p5s4.1": {
            "state": "ok"
        },
        "darīt.a-p5292-p5s4.6": {
            "state": "ok"
        },
        "darīt.a-p530-p25s10.2": {
            "state": "ok"
        },
        "darīt.a-p5328-p4s2.8": {
            "state": "ok"
        },
        "darīt.a-p5341-p3s12.2": {
            "state": "ok"
        },
        "darīt.a-p5341-p3s5.5": {
            "state": "ok"
        },
        "darīt.a-p5406-p2s1.1": {
            "state": "ok"
        },
        "darīt.a-p5446-p3s2.7": {
            "state": "ok"
        },
        "darīt.a-p633-p9s5.21": {
            "state": "ok"
        },
        "darīt.a-p656-p33s2.2": {
            "state": "ok"
        },
        "darīt.a-p6724-p9s3.3": {
            "state": "ok"
        },
        "darīt.a-p680-p14s6.11": {
            "state": "ok"
        },
        "darīt.a-p680-p14s6.7": {
            "state": "ok"
        },
        "darīt.a-p6938-p4s1.16": {
            "state": "ok"
        },
        "darīt.a-p7263-p1s3.1": {
            "state": "ok"
        },
        "darīt.a-p7583-p6s2.1": {
            "state": "ok"
        },
        "darīt.a-p7583-p6s3.0": {
            "state": "ok"
        },
        "darīt.a-p7947-p4s3.13": {
            "state": "ok"
        },
        "darīt.a-p7950-p4s6.6": {
            "state": "ok"
        },
        "darīt.a-p7950-p4s8.9": {
            "state": "ok"
        },
        "darīt.a-p8072-p6s2.7": {
            "state": "ok"
        },
        "darīt.a-p8647-p15s9.10": {
            "state": "ok"
        },
        "darīt.a-p8759-p4s1.12": {
            "state": "ok"
        },
        "darīt.a-p878-p30s1.11": {
            "state": "ok"
        },
        "darīt.a-p9196-p7s9.26": {
            "state": "ok"
        },
        "darīt.a-p9570-p1s4.6": {
            "state": "ok"
        },
        "darīt.a-s14-p122s3.1": {
            "state": "ok"
        },
        "darīt.a-s166-p13s3.3": {
            "state": "ok"
        },
        "darīt.a-s166-p13s3.7": {
            "state": "ok"
        },
        "darīt.a-s25-p11s7.25": {
            "state": "ok"
        },
        "darīt.a-s25-p9s15.3": {
            "state": "ok"
        },
        "darīt.a-s28-p5s4.8": {
            "state": "ok"
        },
        "darīt.a-s6-p8s2.1": {
            "state": "ok"
        },
        "darīt.a-s8-p159s4.17": {
            "state": "ok"
        },
        "darīt.a-s8-p74s3.14": {
            "state": "ok"
        },
        "darīt.a-s93-p5s2.11": {
            "state": "ok"
        },
        "darīt.a-s98-p9s3.17": {
            "state": "ok"
        },
        "darīt.a-z106-p257s9.11": {
            "state": "ok"
        },
        "darīt.a-z106-p265s2.10": {
            "state": "ok"
        },
        "darīt.a-z109-p132s11.26": {
            "state": "ok"
        }
    }
}