{
    "done": false,
    "elements": {
        "Created_entity - nsubj:pass": null,
        "Created_entity - obj": null,
        "Creator - nsubj": null,
        "Place - obl": null,
        "Time - obl": null
    },
    "predicate": null,
    "samples": {
        "izgatavot.a-p1550-p3s1.14": {
            "state": "ok"
        },
        "izgatavot.a-p19715-p3s1.5": {
            "state": "ok"
        },
        "izgatavot.a-p3759-p5s1.6": {
            "state": "ok"
        },
        "izgatavot.a-p6726-p3s1.1": {
            "state": "ok"
        },
        "izgatavot.a-z48-p28s10.11": {
            "state": "ok"
        },
        "izgatavot.a-z48-p28s12.8": {
            "state": "ok"
        },
        "izgatavot.a-z48-p28s9.41": {
            "state": "ok"
        }
    }
}