{
    "done": false,
    "elements": {
        "Cognizer - flat:name": null,
        "Cognizer - nsubj": null,
        "Opinion - ccomp": null,
        "Opinion - iobj": null,
        "Opinion - parataxis": null,
        "Opinion - xcomp": null
    },
    "predicate": null,
    "samples": {
        "spriest.a-d21-p17s3.1": {
            "state": "ok"
        },
        "spriest.a-p1149-p17s4.24": {
            "state": "ok"
        },
        "spriest.a-p1178-p6s1.2": {
            "state": "ok"
        },
        "spriest.a-p1810-p3s4.12": {
            "state": "ok"
        },
        "spriest.a-p586-p18s10.7": {
            "state": "ok"
        }
    }
}