{
    "done": false,
    "elements": {
        "Perceiver_passive - csubj": "err_fn",
        "Perceiver_passive - nsubj": "A0-PPT",
        "Phenomenon - advcl": "A1-PPT",
        "Phenomenon - ccomp": "A1-PPT",
        "Phenomenon - nsubj": "A1-PPT",
        "Phenomenon - obj": "A1-PPT",
        "Place - obl": "AM-LOC",
        "Time - advmod": "AM-TMP",
        "Time - obl": "AM-TMP"
    },
    "predicate": "feel.01",
    "samples": {
        "just.a-c60-p19s6.2": {
            "state": "ok"
        },
        "just.a-c61-p79s2.3": {
            "state": "ok"
        },
        "just.a-d112-p32s10.1": {
            "state": "ok"
        },
        "just.a-d115-p43s3.4": {
            "state": "ok"
        },
        "just.a-d115-p59s7.6": {
            "state": "ok"
        },
        "just.a-d129-p376s1.0": {
            "state": "ok"
        },
        "just.a-d144-p3s4.0": {
            "state": "ok"
        },
        "just.a-d199-p80s1.1": {
            "state": "ok"
        },
        "just.a-d200-p25s1.1": {
            "state": "ok"
        },
        "just.a-d25-p18s3.3": {
            "state": "ok"
        },
        "just.a-d58-p81s1.3": {
            "state": "ok"
        },
        "just.a-d83-p147s4.1": {
            "state": "ok"
        },
        "just.a-d85-p142s7.12": {
            "state": "ok"
        },
        "just.a-p1292-p9s8.3": {
            "state": "ok"
        },
        "just.a-p14174-p35s2.6": {
            "state": "ok"
        },
        "just.a-p1465-p4s20.2": {
            "state": "ok"
        },
        "just.a-p5341-p3s4.1": {
            "state": "ok"
        },
        "just.a-p8385-p22s3.1": {
            "state": "ok"
        },
        "just.a-p9081-p4s1.2": {
            "state": "ok"
        },
        "just.a-p9777-p2s2.4": {
            "state": "ok"
        }
    }
}