{
    "done": false,
    "elements": {
        "Addressee - iobj": null,
        "Addressee - obl": null,
        "Message - nsubj": null,
        "Message - nsubj:pass": null,
        "Message - obj": null,
        "Speaker - nsubj": null,
        "Speaker - root": null,
        "Time - obl": null
    },
    "predicate": null,
    "samples": [
        "uzdot.a-d117-p4s2",
        "uzdot.a-d134-p120s3",
        "uzdot.a-d199-p77s1",
        "uzdot.a-d199-p90s1",
        "uzdot.a-d199-p90s3",
        "uzdot.a-d200-p35s3",
        "uzdot.a-d200-p38s1",
        "uzdot.a-d200-p45s1",
        "uzdot.a-d200-p46s1",
        "uzdot.a-p2948-p4s3"
    ]
}