{
    "done": true,
    "elements": {
        "Agent - nsubj": "A0-PAG",
        "Agent - obj": "A0-PAG",
        "Attribute - obj": "A1-PPT",
        "Phenomenon - nsubj": "A1-PPT",
        "Phenomenon - nsubj:pass": "A1-PPT",
        "Phenomenon - obj": "A1-PPT",
        "Place - advmod": "AM-LOC",
        "Place - obl": "AM-LOC",
        "Time - advmod": "AM-TMP",
        "Time - obl": "AM-TMP"
    },
    "predicate": "record.01",
    "samples": {
        "fiksēt.a-d121-p251s1.37": {
            "state": "ok"
        },
        "fiksēt.a-p10725-p4s2.10": {
            "state": "ok"
        },
        "fiksēt.a-p15228-p8s3.2": {
            "state": "ok"
        },
        "fiksēt.a-p3469-p18s2.8": {
            "state": "ok"
        },
        "fiksēt.a-z46-p11s7.11": {
            "state": "ok"
        },
        "fiksēt.a-z46-p19s3.21": {
            "state": "ok"
        },
        "fiksēt.a-z99-p16s6.3": {
            "state": "ok"
        }
    }
}