{
    "done": false,
    "elements": {
        "Agent - nsubj": null,
        "Agent - obj": null,
        "Cause - nsubj": null,
        "Problem - obj": null,
        "Time - obl": null
    },
    "predicate": null,
    "samples": [
        "risināt.a-d200-p4s5",
        "risināt.a-p1472-p3s4",
        "risināt.a-p1536-p4s2",
        "risināt.a-p164-p17s2",
        "risināt.a-p3432-p11s3",
        "risināt.a-p3762-p36s5",
        "risināt.a-p740-p18s1",
        "risināt.a-s8-p74s2",
        "risināt.a-z21-p37s1"
    ]
}