{
    "done": true,
    "elements": {
        "Agent - iobj": "A0-PAG",
        "Agent - nsubj": "A0-PAG",
        "Theme - obj": "A1-PPT",
        "Time - obl": "AM-TMP"
    },
    "predicate": "retain.01",
    "samples": {
        "saglabāt.a-c58-p41s4.16": {
            "state": "ok"
        },
        "saglabāt.a-c60-p10s3.44": {
            "state": "ok"
        },
        "saglabāt.a-d200-p99s5.8": {
            "state": "ok"
        },
        "saglabāt.a-d21-p20s2.4": {
            "state": "ok"
        },
        "saglabāt.a-p11008-p16s4.19": {
            "state": "ok"
        },
        "saglabāt.a-p1159-p7s2.3": {
            "state": "ok"
        },
        "saglabāt.a-p12458-p1s13.11": {
            "state": "ok"
        },
        "saglabāt.a-p140-p13s3.11": {
            "state": "ok"
        },
        "saglabāt.a-p14157-p9s6.6": {
            "state": "ok"
        },
        "saglabāt.a-p14162-p16s2.11": {
            "state": "ok"
        },
        "saglabāt.a-p14343-p7s3.10": {
            "state": "ok"
        },
        "saglabāt.a-p14692-p6s1.7": {
            "state": "ok"
        },
        "saglabāt.a-p2674-p16s4.14": {
            "state": "ok"
        },
        "saglabāt.a-p2968-p10s3.15": {
            "state": "ok"
        },
        "saglabāt.a-p2969-p8s2.2": {
            "state": "ok"
        },
        "saglabāt.a-p3159-p1s2.13": {
            "state": "ok"
        },
        "saglabāt.a-p3469-p19s8.5": {
            "state": "ok"
        },
        "saglabāt.a-p3762-p24s5.3": {
            "state": "ok"
        },
        "saglabāt.a-p3772-p8s1.14": {
            "state": "ok"
        },
        "saglabāt.a-p378-p11s11.3": {
            "state": "ok"
        },
        "saglabāt.a-p512-p8s3.6": {
            "state": "ok"
        },
        "saglabāt.a-p5549-p3s1.2": {
            "state": "ok"
        },
        "saglabāt.a-p5561-p5s1.4": {
            "state": "ok"
        },
        "saglabāt.a-p6819-p1s2.26": {
            "state": "ok"
        },
        "saglabāt.a-p9913-p20s2.4": {
            "state": "ok"
        },
        "saglabāt.a-z102-p34s2.3": {
            "state": "ok"
        }
    }
}