{
    "done": true,
    "elements": {
        "Experiencer - iobj": "A1-PPT",
        "Experiencer - obj": "A1-PPT",
        "Place - obl": "AM-LOC",
        "Stimulus - nsubj": "A0-PAG",
        "Time - iobj": "AM-TMP"
    },
    "predicate": "please.01",
    "samples": {
        "priecēt.a-d197-p17s2.4": {
            "state": "ok"
        },
        "priecēt.a-p11857-p1s1.5": {
            "state": "ok"
        },
        "priecēt.a-p12004-p9s1.4": {
            "state": "ok"
        },
        "priecēt.a-p13589-p9s3.11": {
            "state": "ok"
        },
        "priecēt.a-p14923-p6s2.10": {
            "state": "ok"
        },
        "priecēt.a-p18803-p2s2.23": {
            "state": "ok"
        },
        "priecēt.a-p18834-p6s3.17": {
            "state": "ok"
        },
        "priecēt.a-p6362-p3s1.14": {
            "state": "ok"
        }
    }
}