{
    "done": false,
    "elements": {},
    "predicate": null,
    "samples": {
        "pārņemt.a-d199-p28s1.13": {
            "state": "ok"
        },
        "pārņemt.a-d199-p43s1.15": {
            "state": "ok"
        },
        "pārņemt.a-p1299-p2s1.7": {
            "state": "ok"
        },
        "pārņemt.a-p1596-p6s1.11": {
            "state": "ok"
        },
        "pārņemt.a-p2136-p3s1.30": {
            "state": "ok"
        },
        "pārņemt.a-p3427-p8s9.11": {
            "state": "ok"
        },
        "pārņemt.a-p3739-p13s1.10": {
            "state": "ok"
        }
    }
}